command/command.py
doge/N.py
doge/Plain Craft Launcher 2.exe
doge/charts_render.py
doge/dogheados.py
doge/geckodriver.log
doge/htmlcreater.py
doge/icon (2).gif
doge/icon.ico
doge/media_player.py
doge/python_stript.py
doge/test.py
doge/textcreater.py
doge/settings/main.setting
downloader-python/__init__.py
downloader-python/downloader.py
downloader-python/downloader.ui
downloader-python/icon.bmp
downloader-python/load_text.py
downloader-python/main.py
downloader-python/mcpi_test.py
downloader-python/pip_install.py
downloader-python/test.py
downloader-python/web.py
downloader-python/web_runner.py
downloader-python/language/en-us.lang
downloader-python/language/zh-cn.lang
downloader-python/log/2021-09-25-09-09-10.log
downloader-python/log/2021-09-25-10-10-01.log
downloader-python/log/2021-09-25-10-10-02.log
downloader-python/log/2021-09-25-10-10-07.log
downloader-python/log/2021-09-25-10-10-11.log
downloader-python/log/2021-09-25-10-10-20.log
downloader-python/log/2021-09-25-10-10-21.log
downloader-python/log/2021-09-25-10-10-26.log
downloader-python/log/2021-09-25-10-10-29.log
downloader-python/log/2021-09-25-10-10-32.log
downloader-python/log/2021-09-25-10-10-35.log
downloader-python/log/2021-09-25-10-10-36.log
downloader-python/log/2021-09-25-10-10-41.log
downloader-python/log/2021-09-25-10-10-45.log
downloader-python/log/2021-09-25-10-10-47.log
downloader-python/log/2021-09-25-10-10-53.log
downloader-python/log/2021-09-25-10-10-59.log
downloader-python/log/2021-09-25-11-11-01.log
downloader-python/log/2021-09-25-11-11-02.log
downloader-python/log/2021-09-25-11-11-03.log
downloader-python/log/2021-09-25-11-11-04.log
downloader-python/log/2021-09-25-11-11-05.log
downloader-python/log/2021-09-25-11-11-08.log
downloader-python/log/2021-09-25-11-11-09.log
downloader-python/log/2021-09-25-11-11-12.log
downloader-python/log/2021-09-25-11-11-16.log
downloader-python/log/2021-09-25-11-11-17.log
downloader-python/log/2021-09-25-11-11-18.log
downloader_python-1.11.dist-info/LICENSE
downloader_python-1.11.dist-info/METADATA
downloader_python-1.11.dist-info/WHEEL
downloader_python-1.11.dist-info/top_level.txt
downloader_python-1.11.dist-info/RECORD
