Metadata-Version: 2.1
Name: downloader-python
Version: 1.11
Summary: An fast downloader with ui.
Home-page: https://github.com
Author: mc_creater
Author-email: guoxiuchen20170402@163.com
License: MIT
Platform: UNKNOWN
Classifier: Programming Language :: Python :: 3.6
Classifier: Programming Language :: Python :: 3.7
Classifier: Programming Language :: Python :: 3.8
Classifier: Programming Language :: Python :: 3.9
Requires-Python: >=3.6
License-File: LICENSE
Requires-Dist: PyQt5
Requires-Dist: requests
Requires-Dist: bs4
Requires-Dist: lxml
Requires-Dist: mcpi
